cefpython3/LICENSE.txt
cefpython3/License
cefpython3/README.txt
cefpython3/__init__.py
cefpython3/cefpython_py38.so
cefpython3/debug.log
cefpython3/subprocess
cefpython3/widevinecdmadapter.plugin
cefpython3/Chromium Embedded Framework.framework/Chromium Embedded Framework
cefpython3/Chromium Embedded Framework.framework/Resources/Info.plist
cefpython3/Chromium Embedded Framework.framework/Resources/cef.pak
cefpython3/Chromium Embedded Framework.framework/Resources/cef_100_percent.pak
cefpython3/Chromium Embedded Framework.framework/Resources/cef_200_percent.pak
cefpython3/Chromium Embedded Framework.framework/Resources/cef_extensions.pak
cefpython3/Chromium Embedded Framework.framework/Resources/devtools_resources.pak
cefpython3/Chromium Embedded Framework.framework/Resources/icudtl.dat
cefpython3/Chromium Embedded Framework.framework/Resources/natives_blob.bin
cefpython3/Chromium Embedded Framework.framework/Resources/snapshot_blob.bin
cefpython3/Chromium Embedded Framework.framework/Resources/v8_context_snapshot.bin
cefpython3/Chromium Embedded Framework.framework/Resources/am.lproj/locale.pak
cefpython3/Chromium Embedded Framework.framework/Resources/ar.lproj/locale.pak
cefpython3/Chromium Embedded Framework.framework/Resources/bg.lproj/locale.pak
cefpython3/Chromium Embedded Framework.framework/Resources/bn.lproj/locale.pak
cefpython3/Chromium Embedded Framework.framework/Resources/ca.lproj/locale.pak
cefpython3/Chromium Embedded Framework.framework/Resources/cs.lproj/locale.pak
cefpython3/Chromium Embedded Framework.framework/Resources/da.lproj/locale.pak
cefpython3/Chromium Embedded Framework.framework/Resources/de.lproj/locale.pak
cefpython3/Chromium Embedded Framework.framework/Resources/el.lproj/locale.pak
cefpython3/Chromium Embedded Framework.framework/Resources/en.lproj/locale.pak
cefpython3/Chromium Embedded Framework.framework/Resources/en_GB.lproj/locale.pak
cefpython3/Chromium Embedded Framework.framework/Resources/es.lproj/locale.pak
cefpython3_for_python_3.8.10_unofficial-66.1.dist-info/METADATA
cefpython3_for_python_3.8.10_unofficial-66.1.dist-info/WHEEL
cefpython3_for_python_3.8.10_unofficial-66.1.dist-info/top_level.txt
cefpython3_for_python_3.8.10_unofficial-66.1.dist-info/RECORD
