Metadata-Version: 2.1
Name: cefpython3-for-python-3.8.10-unofficial
Version: 66.1
Summary: GUI toolkit for embedding a Chromium widget in desktop applications
Home-page: https://github.com/kletel/cefpython
Author: Sébastien DROUIN
Author-email: sebastien@kletel.net
License: BSD 3-clause
Download-URL: https://github.com/kletel/cefpython/releases
Platform: macosx-10.9-x86_64
Classifier: Development Status :: 6 - Mature
Classifier: Intended Audience :: Developers
Classifier: License :: OSI Approved :: BSD License
Classifier: Natural Language :: English
Classifier: Operating System :: MacOS :: MacOS X
Classifier: Operating System :: Microsoft :: Windows
Classifier: Operating System :: POSIX :: Linux
Classifier: Programming Language :: Python :: 2.7
Classifier: Programming Language :: Python :: 3.4
Classifier: Programming Language :: Python :: 3.5
Classifier: Programming Language :: Python :: 3.6
Classifier: Programming Language :: Python :: 3.7
Classifier: Programming Language :: Python :: 3.8
Classifier: Programming Language :: Python :: 3.9
Classifier: Topic :: Desktop Environment
Classifier: Topic :: Internet
Classifier: Topic :: Internet :: WWW/HTTP
Classifier: Topic :: Internet :: WWW/HTTP :: Browsers
Classifier: Topic :: Multimedia
Classifier: Topic :: Software Development :: User Interfaces
